setup.py
udi_probability/Binomialdistribution.py
udi_probability/Gaussiandistribution.py
udi_probability/Generaldistribution.py
udi_probability/__init__.py
udi_probability.egg-info/PKG-INFO
udi_probability.egg-info/SOURCES.txt
udi_probability.egg-info/dependency_links.txt
udi_probability.egg-info/not-zip-safe
udi_probability.egg-info/top_level.txt