Metadata-Version: 1.0
Name: udi-probability
Version: 0.1
Summary: Gaussian and Binomial distributions
Home-page: UNKNOWN
Author: Pranjal Raj
Author-email: pranjalraj0046@gmail.com
License: UNKNOWN
Platform: UNKNOWN
